{
  "blog": [
    {
      "title": "title  dddfdg",
      "Category": "g",
      "Author": "fg",
      "Desc": "e",
      "id": "1"
    },
    {
      "id": "2",
      "title": "title2",
      "Category": "Book2",
      "Author": "kranti2",
      "Desc": "Lorem ispum2"
    },
    {
      "title": "test",
      "Category": "test",
      "Author": "test",
      "Desc": "test",
      "id": "5Kkwd09"
    },
    {
      "title": "test2",
      "Category": "test2",
      "Author": "test2",
      "Desc": "test2",
      "id": "LWL_Ti1"
    },
    {
      "title": "dfdfdf",
      "Category": "fdfdf",
      "Author": "",
      "Desc": "",
      "id": "JELCv9e"
    },
    {
      "title": "dfdfdf",
      "Category": "fdfdf",
      "Author": "sdsd",
      "Desc": "sdfsd",
      "id": "K1t_6F2"
    },
    {
      "title": "dfdfdf",
      "Category": "fdfdf",
      "Author": "sdsd",
      "Desc": "sdfsd",
      "id": "-wewXPH"
    },
    {
      "title": "",
      "Category": "",
      "Author": "",
      "Desc": "",
      "id": "wcaN8oi"
    },
    {
      "title": "test",
      "Category": "tste",
      "Author": "tst",
      "Desc": "tse",
      "id": "Sk9onUJ"
    },
    {
      "title": "stesta",
      "Category": "stts",
      "Author": "st",
      "Desc": "st",
      "id": "XYv1lr9"
    },
    {
      "title": "dsssss",
      "Category": "sdf",
      "Author": "sdf",
      "Desc": "sdf",
      "id": "uGKCYAS"
    },
    {
      "title": "Examples of Blogs – Inspiration for New Bloggers",
      "Category": "News",
      "Author": "Jamie Spencer",
      "Desc": "If you’re thinking of starting a blog of your own, but just don’t have a clue on what to blog about, then fear not!\n\nIn this article, I have included a whole load of blog examples from a wide variety of different niches, all run on different blogging platforms like WordPress, Joomla! and Drupal.\n\nSince the beginning of the internet, millions and millions and millions of blogs have been created. Many have died due to lost interest or their owners giving up on the idea, while others have thrived and continue to grow, making money and earning their owners a steady income. It’s a constant evolution of content that keeps people coming back for more, especially if these blogs contact highly resourceful material that people find useful and interesting.",
      "id": "3V65IuU"
    },
    {
      "title": "tyre",
      "Category": "machine",
      "Author": "Kranti",
      "Desc": "kjhjhkhkjh",
      "id": "5fgqBRi"
    }
  ]
}